plnq/__init__.py
plnq/__main__.py
plnq/plnq.py
plnq/answer/__init__.py
plnq/answer/answer.py
plnq/answer/float_answer.py
plnq/answer/inline_answer.py
plnq/answer/re_answer.py
plnq/quiz_template/__init__.py
plnq/quiz_template/info.json
plnq/quiz_template/question.html
plnq/quiz_template/server.py
plnq/quiz_template/tests/__init__.py
plnq/quiz_template/tests/ans.py
plnq/quiz_template/tests/initial_code.py
plnq/quiz_template/tests/setup_code.py
plnq/quiz_template/tests/test.py
plnq/quiz_template/workspace/learning_target.ipynb
plnq/quiz_template/workspace/playspace.ipynb
plnq_mock/__init__.py
plnq_gvsu-2.0.3.dist-info/METADATA
plnq_gvsu-2.0.3.dist-info/WHEEL
plnq_gvsu-2.0.3.dist-info/entry_points.txt
plnq_gvsu-2.0.3.dist-info/licenses/LICENSE
plnq_gvsu-2.0.3.dist-info/RECORD
