Metadata-Version: 2.4
Name: plnq-gvsu
Version: 2.0.3
Summary: Builds PrairieLearn questions containing auto-graded Jupyter notebooks
Project-URL: Homepage, https://github.com/kurmasz/plnq
Project-URL: Issues, https://github.com/kurmasz/plnq/issues
Author-email: Zachary Kurmas <kurmasz@gvsu.edu>
License-Expression: GPL-3.0-or-later
License-File: LICENSE
Classifier: Development Status :: 2 - Pre-Alpha
Classifier: Environment :: Console
Classifier: Intended Audience :: Education
Classifier: Operating System :: OS Independent
Classifier: Programming Language :: Python :: 3
Requires-Python: >=3.9
Requires-Dist: nbformat>=5.10.4
